pysounds/__init__.py
pysounds-1.1.1.dist-info/LICENSE.txt
pysounds-1.1.1.dist-info/METADATA
pysounds-1.1.1.dist-info/WHEEL
pysounds-1.1.1.dist-info/top_level.txt
pysounds-1.1.1.dist-info/RECORD
