Metadata-Version: 2.1
Name: pysounds
Version: 1.1.1
Summary: play various sounds with python (beta)
Author-email: Leander Kafemann <leander@kafemann.berlin>
Project-URL: Homepage, https://github.com/LeanderKafemann/pysounds
Classifier: Programming Language :: Python :: 3
Classifier: License :: OSI Approved :: MIT License
Classifier: Operating System :: OS Independent
Requires-Python: >=3.11
License-File: LICENSE.txt
